CHANGELOG.md
LICENSE
MANIFEST.in
README.md
pylintrc
requirements-dev.txt
requirements.txt
setup.cfg
setup.py
tox.ini
chmod_monkey/__init__.py
chmod_monkey/__version__.py
chmod_monkey/operation.py
chmod_monkey/parser.py
chmod_monkey.egg-info/PKG-INFO
chmod_monkey.egg-info/SOURCES.txt
chmod_monkey.egg-info/dependency_links.txt
chmod_monkey.egg-info/requires.txt
chmod_monkey.egg-info/top_level.txt
chmod_monkey.egg-info/zip-safe
tests/test_init.py
tests/test_operation.py
tests/test_parser.py