Metadata-Version: 2.1
Name: chmod-monkey
Version: 1.1.1
Summary: Add support for `os.chmod('script.sh', 'ug+x')` syntax style.
Home-page: https://github.com/Toilal/python-chmod-monkey
Author: Rémi Alvergnat
Author-email: toilal.dev@gmail.com
License: MIT
Download-URL: https://pypi.python.org/packages/source/g/python-chmod-monkey/python-chmod-monkey-1.1.1.tar.gz
Keywords: chmod monkeypatch str string
Platform: UNKNOWN
Classifier: Development Status :: 3 - Alpha
Classifier: License :: OSI Approved :: MIT License
Classifier: Operating System :: OS Independent
Classifier: Intended Audience :: Developers
Classifier: Programming Language :: Python :: 2.7
Classifier: Programming Language :: Python :: 3
Classifier: Programming Language :: Python :: 3.5
Classifier: Programming Language :: Python :: 3.6
Classifier: Programming Language :: Python :: 3.7
Classifier: Programming Language :: Python :: 3.8
Classifier: Topic :: Software Development :: Libraries :: Python Modules
Provides-Extra: dev
